chatmol/__init__.py
chatmol/pymol_server.py
chatmol/utils.py
chatmol-0.2.3.dist-info/METADATA
chatmol-0.2.3.dist-info/WHEEL
chatmol-0.2.3.dist-info/top_level.txt
chatmol-0.2.3.dist-info/RECORD
