Metadata-Version: 2.1
Name: chatmol
Version: 0.2.3
Summary: A package for ChatMol
Home-page: https://github.com/JinyuanSun/ChatMol/chatmol_pkg
Author: The ChatMol Team
Author-email: jinyuansun@chatmol.org
Keywords: chatmol
Requires-Dist: requests
Requires-Dist: openai >=1.3.9
Requires-Dist: anthropic >=0.19.1
Requires-Dist: streamlit >=1.35.0
